redstork/__init__.py
redstork/bindings.py
redstork/dict_changed.py
redstork/document.py
redstork/font.py
redstork/glyph.py
redstork/page.py
redstork/pageobject.py
redstork/pdfium_version.txt
redstork/so.py
redstork/unicode_map.py
redstork/test/__init__.py
redstork/test/test_dict_changed.py
redstork/test/test_document.py
redstork/test/test_font.py
redstork/test/test_glyph.py
redstork/test/test_page.py
redstork/test/test_text.py
redstork/test/test_textobject.py
redstork/test/test_unicode_map.py
redstork-0.0.41.dist-info/LICENSE
redstork-0.0.41.dist-info/METADATA
redstork-0.0.41.dist-info/WHEEL
redstork-0.0.41.dist-info/top_level.txt
redstork-0.0.41.dist-info/RECORD
