Metadata-Version: 2.1
Name: redstork
Version: 0.0.41
Summary: Parsing PDF files with PDFium
Home-page: https://github.com/innodatalabs/redstork
Author: Mike Kroutikov
Author-email: mkroutikov@innodata.com
License: MIT
Platform: UNKNOWN
Classifier: Development Status :: 4 - Beta
Classifier: Intended Audience :: Developers
Classifier: Programming Language :: Python :: 3 :: Only
Classifier: Programming Language :: Python :: 3.7
Classifier: Programming Language :: Python :: 3.8
Classifier: License :: OSI Approved :: MIT License
Classifier: Operating System :: OS Independent
Requires-Python: >=3.6
